odoo/addons/sale_wishlist/README.rst
odoo/addons/sale_wishlist/__init__.py
odoo/addons/sale_wishlist/__manifest__.py
odoo/addons/sale_wishlist/i18n/es.po
odoo/addons/sale_wishlist/i18n/fr_FR.po
odoo/addons/sale_wishlist/i18n/it.po
odoo/addons/sale_wishlist/i18n/sale_wishlist.pot
odoo/addons/sale_wishlist/models/__init__.py
odoo/addons/sale_wishlist/models/product_set.py
odoo/addons/sale_wishlist/models/res_partner.py
odoo/addons/sale_wishlist/readme/CONTRIBUTORS.md
odoo/addons/sale_wishlist/readme/CREDITS.md
odoo/addons/sale_wishlist/readme/DESCRIPTION.md
odoo/addons/sale_wishlist/readme/USAGE.md
odoo/addons/sale_wishlist/static/description/icon.png
odoo/addons/sale_wishlist/static/description/index.html
odoo/addons/sale_wishlist/tests/__init__.py
odoo/addons/sale_wishlist/tests/test_wishlist.py
odoo/addons/sale_wishlist/views/partner.xml
odoo/addons/sale_wishlist/views/product_set.xml
odoo_addon_sale_wishlist-18.0.1.0.0.2.dist-info/METADATA
odoo_addon_sale_wishlist-18.0.1.0.0.2.dist-info/WHEEL
odoo_addon_sale_wishlist-18.0.1.0.0.2.dist-info/top_level.txt
odoo_addon_sale_wishlist-18.0.1.0.0.2.dist-info/RECORD
